real_robots/__init__.py
real_robots/cli.py
real_robots/evaluate.py
real_robots/generate_goals.py
real_robots/policy.py
real_robots/videomaker.py
real_robots/data/__init__.py
real_robots/data/kuka_gripper_description/meshes/Blue.png
real_robots/data/kuka_gripper_description/meshes/Grey.png
real_robots/data/kuka_gripper_description/meshes/LightGrey.png
real_robots/data/kuka_gripper_description/meshes/OrangeColor.png
real_robots/data/kuka_gripper_description/meshes/banana.blend
real_robots/data/kuka_gripper_description/meshes/banana.mtl
real_robots/data/kuka_gripper_description/meshes/banana.obj
real_robots/data/kuka_gripper_description/meshes/banana.png
real_robots/data/kuka_gripper_description/meshes/base.blend
real_robots/data/kuka_gripper_description/meshes/base.mtl
real_robots/data/kuka_gripper_description/meshes/base.obj
real_robots/data/kuka_gripper_description/meshes/base.stl
real_robots/data/kuka_gripper_description/meshes/cube.blend
real_robots/data/kuka_gripper_description/meshes/cube.mtl
real_robots/data/kuka_gripper_description/meshes/cube.obj
real_robots/data/kuka_gripper_description/meshes/cube.png
real_robots/data/kuka_gripper_description/meshes/finger_0.blend
real_robots/data/kuka_gripper_description/meshes/finger_0.mtl
real_robots/data/kuka_gripper_description/meshes/finger_0.obj
real_robots/data/kuka_gripper_description/meshes/finger_0.stl
real_robots/data/kuka_gripper_description/meshes/finger_1.blend
real_robots/data/kuka_gripper_description/meshes/finger_1.mtl
real_robots/data/kuka_gripper_description/meshes/finger_1.obj
real_robots/data/kuka_gripper_description/meshes/finger_1.stl
real_robots/data/kuka_gripper_description/meshes/hammer.blend
real_robots/data/kuka_gripper_description/meshes/hammer.mtl
real_robots/data/kuka_gripper_description/meshes/hammer.obj
real_robots/data/kuka_gripper_description/meshes/hammer.png
real_robots/data/kuka_gripper_description/meshes/link0.blend
real_robots/data/kuka_gripper_description/meshes/link0.mtl
real_robots-0.1.21.dist-info/AUTHORS.rst
real_robots-0.1.21.dist-info/LICENSE
real_robots-0.1.21.dist-info/METADATA
real_robots-0.1.21.dist-info/WHEEL
real_robots-0.1.21.dist-info/entry_points.txt
real_robots-0.1.21.dist-info/top_level.txt
real_robots-0.1.21.dist-info/RECORD
