Metadata-Version: 2.1
Name: real-robots
Version: 0.1.21
Summary: Robots that learn to interact with the environment autonomously
Home-page: https://github.com/aicrowd/real_robots
Author: S.P. Mohanty
Author-email: mohanty@aicrowd.com
License: MIT license
Keywords: real_robots
Platform: UNKNOWN
Classifier: Development Status :: 2 - Pre-Alpha
Classifier: Intended Audience :: Developers
Classifier: License :: OSI Approved :: MIT License
Classifier: Natural Language :: English
Classifier: Programming Language :: Python :: 3.5
Classifier: Programming Language :: Python :: 3.6
Classifier: Programming Language :: Python :: 3.7
Requires-Dist: Click (>=6.0)
Requires-Dist: gym
Requires-Dist: pybullet
Requires-Dist: numpy
Requires-Dist: tqdm
Requires-Dist: aicrowd-api
Requires-Dist: pillow
Requires-Dist: pyinterval
